mslogger-1.0.0.dev1.dist-info/DESCRIPTION.rst
mslogger-1.0.0.dev1.dist-info/METADATA
mslogger-1.0.0.dev1.dist-info/RECORD
mslogger-1.0.0.dev1.dist-info/WHEEL
mslogger-1.0.0.dev1.dist-info/metadata.json
mslogger-1.0.0.dev1.dist-info/top_level.txt
musicstory/logger/__init__.py
